pycompileo/__init__.py
pycompileo/compilation/__init__.py
pycompileo/compilation/compiler.py
pycompileo/compilation/decompiler.py
pycompileo/obfuscation/__init__.py
pycompileo/obfuscation/multiversion_obfuscate.py
pycompileo/obfuscation/obfuscate.py
pycompileo/obfuscation/obfuscate_module.py
pycompileo/obfuscation/obfuscate_package.py
pycompileo/scaffoldy/__init__.py
pycompileo/scaffoldy/src/__init__.py
pycompileo/scaffoldy/src/secret.py
pycompileo-1.3.8.dist-info/METADATA
pycompileo-1.3.8.dist-info/WHEEL
pycompileo-1.3.8.dist-info/top_level.txt
pycompileo-1.3.8.dist-info/RECORD
