Metadata-Version: 2.1
Name: pycompileo
Version: 1.3.8
Summary: Python Code Obfuscator.
Author: Schkimansky
Author-email: <ahmadchawla1432@gmail.com>
Keywords: python,compile,decompile,proprietarify,obfuscate,code,obfuscation
Classifier: Development Status :: 5 - Production/Stable
Classifier: Intended Audience :: Developers
Classifier: Programming Language :: Python :: 3
Classifier: Operating System :: Unix
Classifier: Operating System :: MacOS :: MacOS X
Classifier: Operating System :: Microsoft :: Windows
